psusigner/__init__.py
psusigner/exception.py
psusigner/psucms.py
psusigner/psuhsm.py
psusigner/signers.py
psusigner-0.1.9.dist-info/METADATA
psusigner-0.1.9.dist-info/WHEEL
psusigner-0.1.9.dist-info/RECORD
