Metadata-Version: 2.1
Name: psusigner
Version: 0.1.9
Summary: PSU Signer
Author: Thanathip Limna
Author-email: thanathip.l@coe.psu.ac.th
Requires-Python: >=3.11,<4.0
Classifier: Programming Language :: Python :: 3
Classifier: Programming Language :: Python :: 3.11
Requires-Dist: endesive (>=2.0.16,<3.0.0)
Requires-Dist: pyjwt (>=2.7.0,<3.0.0)
Requires-Dist: requests (>=2.31.0,<3.0.0)
